statistica123/init.py
statistica123-0.2.dist-info/METADATA
statistica123-0.2.dist-info/WHEEL
statistica123-0.2.dist-info/top_level.txt
statistica123-0.2.dist-info/RECORD
