Metadata-Version: 2.1
Name: statistica123
Version: 0.2
Summary: this is a package
Author: Abdul Sami
License: UNKNOWN
Platform: UNKNOWN
